comet_labs/__init__.py
comet_labs/ai_helpers.py
comet_labs/cli.py
comet_labs/jira.py
comet_labs/prompts.py
comet_labs/utils.py
comet_labs-0.1.6.dist-info/LICENSE
comet_labs-0.1.6.dist-info/METADATA
comet_labs-0.1.6.dist-info/WHEEL
comet_labs-0.1.6.dist-info/entry_points.txt
comet_labs-0.1.6.dist-info/RECORD
