Metadata-Version: 2.1
Name: comet_labs
Version: 0.1.6
Summary: A Python package for comet-related functionalities
Home-page: https://github.com/Sahilsingh0808/comet
License: MIT
Keywords: git,ai,commit-messages
Author: Sahil
Author-email: sahil85.10s@gmail.com
Requires-Python: >=3.8,<4.0
Classifier: License :: OSI Approved :: MIT License
Classifier: Programming Language :: Python :: 3
Classifier: Programming Language :: Python :: 3.8
Classifier: Programming Language :: Python :: 3.9
Classifier: Programming Language :: Python :: 3.10
Classifier: Programming Language :: Python :: 3.11
Classifier: Programming Language :: Python :: 3.12
Classifier: Programming Language :: Python :: 3.13
Requires-Dist: annotated-types (==0.7.0)
Requires-Dist: anyio (==4.7.0)
Requires-Dist: certifi (==2024.8.30)
Requires-Dist: charset-normalizer (==3.4.0)
Requires-Dist: distro (==1.9.0)
Requires-Dist: h11 (==0.14.0)
Requires-Dist: httpcore (==1.0.7)
Requires-Dist: httpx (==0.28.1)
Requires-Dist: idna (==3.10)
Requires-Dist: jiter (==0.8.2)
Requires-Dist: openai (==1.57.4)
Requires-Dist: pydantic (==2.10.3)
Requires-Dist: pydantic_core (==2.27.1)
Requires-Dist: python-dotenv (==1.0.1)
Requires-Dist: requests (==2.32.3)
Requires-Dist: sniffio (==1.3.1)
Requires-Dist: textblob (==0.18.0.post0)
Requires-Dist: tqdm (==4.67.1)
Requires-Dist: typing_extensions (==4.12.2)
Requires-Dist: urllib3 (==2.2.3)
Project-URL: Repository, https://github.com/Sahilsingh0808/comet
